flowvisor/__init__.py
flowvisor/delta_function_node.py
flowvisor/flowvisor.py
flowvisor/flowvisor_config.py
flowvisor/flowvisor_verifier.py
flowvisor/function_node.py
flowvisor/logger.py
flowvisor/sankey.py
flowvisor/time_tracker.py
flowvisor/time_value.py
flowvisor/timer.py
flowvisor/utils.py
flowvisor/cli/__init__.py
flowvisor/cli/add_vis.py
flowvisor/cli/remove_vis.py
flowvisor/cli/vis_delta.py
flowvisor/cli/vis_file.py
FlowVisor-0.3.2.dist-info/LICENSE
FlowVisor-0.3.2.dist-info/METADATA
FlowVisor-0.3.2.dist-info/WHEEL
FlowVisor-0.3.2.dist-info/entry_points.txt
FlowVisor-0.3.2.dist-info/top_level.txt
FlowVisor-0.3.2.dist-info/RECORD
