Metadata-Version: 2.1
Name: FlowVisor
Version: 0.3.2
Summary: Visualize and profile your python code with FlowVisor.
Home-page: https://github.com/cophilot/FlowVisor
Author: cophilot (Philipp B.)
Author-email: <info@philipp-bonin.com>
License: MIT
Keywords: python,flow,visualize,code,flowvisor,profiling,profile,decorator
Platform: UNKNOWN
Classifier: Development Status :: 3 - Alpha
Classifier: Intended Audience :: Developers
Classifier: Programming Language :: Python :: 3
Classifier: Operating System :: Unix
Classifier: Operating System :: MacOS :: MacOS X
Classifier: Operating System :: Microsoft :: Windows
License-File: LICENSE
Requires-Dist: Pillow
Requires-Dist: diagrams (~=0.23.4)
Requires-Dist: pickle-mixin (~=1.0.2)
Requires-Dist: plotly
